minstrel/__init__.py
minstrel/db.py
minstrel/home.py
minstrel/schema.sql
minstrel/settings.py
minstrel/slug.py
minstrel/token.py
minstrel/api/command.py
minstrel/api/instrument.py
minstrel/api/sequence.py
minstrel/api/state.py
minstrel/static/favicon.svg
minstrel/static/open-sans-bold.woff2
minstrel/static/open-sans-medium.woff2
minstrel/static/open-sans-regular.woff2
minstrel/static/site.css
minstrel/templates/404_not_found.html
minstrel/templates/base.htm
minstrel/templates/create_command.html
minstrel/templates/create_instrument.html
minstrel/templates/create_sequence.html
minstrel/templates/create_state.html
minstrel/templates/home.html
minstrel/templates/settings.html
minstrel/templates/update_command.html
minstrel/templates/update_instrument.html
minstrel/templates/update_sequence.html
minstrel/templates/update_state.html
minstrel-0.0.3.dist-info/LICENSE
minstrel-0.0.3.dist-info/METADATA
minstrel-0.0.3.dist-info/WHEEL
minstrel-0.0.3.dist-info/top_level.txt
minstrel-0.0.3.dist-info/RECORD
